README.txt
exceptionlog
medialog
setup.py
setup.pyc
sitelog
sitesWithFileslog
spider.e3p
start-spider.py
SpideyAgent.egg-info/PKG-INFO
SpideyAgent.egg-info/SOURCES.txt
SpideyAgent.egg-info/not-zip-safe
SpideyAgent.egg-info/requires.txt
SpideyAgent.egg-info/top_level.txt
spider/__init__.py
spider/__init__.pyc
spider/controllers.py
spider/controllers.pyc
spider/model.py
spider/model.pyc
spider/spider.py
spider/spider.pyc
spider/config/__init__.py
spider/static/images/favicon.ico
spider/static/images/spiderpy.gif
spider/static/images/tg_under_the_hood.png
spider/templates/CreateUser.pyc
spider/templates/Login.pyc
spider/templates/NewUser.pyc
spider/templates/__init__.py
spider/templates/__init__.pyc
spider/templates/add.kid
spider/templates/add.pyc
spider/templates/added.kid
spider/templates/added.pyc
spider/templates/admin.kid
spider/templates/admin.pyc
spider/templates/authenticateAdmin.kid
spider/templates/authenticateAdmin.pyc
spider/templates/createuser.kid
spider/templates/edit_user.kid
spider/templates/edit_user.pyc
spider/templates/login.kid
spider/templates/login.pyc
spider/templates/master.kid
spider/templates/master.pyc
spider/templates/newuser.kid
spider/templates/newuser.pyc
spider/templates/remove.kid
spider/templates/remove.pyc
spider/templates/results.kid
spider/templates/results.pyc
spider/templates/setInterval.kid
spider/templates/spiderpy.gif
spider/templates/start.kid
spider/templates/start.pyc
spider/templates/stop.kid
spider/templates/stop.pyc
spider/templates/userpage.kid
spider/templates/userpage.pyc
spider/templates/welcome.kid
spider/templates/welcome.pyc
spider/tests/__init__.py
spider/tests/test_controllers.py
spider/tests/test_model.py
spider/tests/test_spider.py
