Metadata-Version: 1.0
Name: SpideyAgent
Version: 0.75
Summary: Each user can run their own threaded search engine and contribute to a global search database searching only the sites they want
Home-page: http://sourceforge.net/projects/pyspider
Author: Ben Hamilton
Author-email: ben.hamilton@gmail.com
License: GPL
Platform: UNKNOWN
Classifier: Development Status :: 3 - Alpha
Classifier: Operating System :: OS Independent
Classifier: Programming Language :: Python
Classifier: Topic :: Software Development :: Libraries :: Python Modules
